README.rst
setup.py
helloJosh/__init__.py
helloJosh/welcome.py
helloJosh.egg-info/PKG-INFO
helloJosh.egg-info/SOURCES.txt
helloJosh.egg-info/dependency_links.txt
helloJosh.egg-info/not-zip-safe
helloJosh.egg-info/top_level.txt