Metadata-Version: 1.1
Name: helloJosh
Version: 0.1
Summary: Python package example
Home-page: http://mywebsite_foo
Author: josh
Author-email: osbornj7@wwu.edu
License: MIT
Keywords: Package Distribution
Platform: UNKNOWN
Classifier: Programming Language :: Python
